{
 "custom_fields": [
  {
   "_assign": null,
   "_comments": null,
   "_liked_by": null,
   "_user_tags": null,
   "allow_in_quick_entry": 0,
   "allow_on_submit": 0,
   "bold": 0,
   "collapsible": 0,
   "collapsible_depends_on": null,
   "columns": 0,
   "creation": "2024-05-27 12:48:08.665875",
   "default": null,
   "depends_on": null,
   "description": null,
   "docstatus": 0,
   "dt": "Purchase Order",
   "fetch_from": null,
   "fetch_if_empty": 0,
   "fieldname": "item_group",
   "fieldtype": "Link",
   "hidden": 0,
   "hide_border": 0,
   "hide_days": 0,
   "hide_seconds": 0,
   "idx": 28,
   "ignore_user_permissions": 0,
   "ignore_xss_filter": 0,
   "in_global_search": 0,
   "in_list_view": 0,
   "in_preview": 0,
   "in_standard_filter": 0,
   "insert_after": "accounting_dimensions_section",
   "is_system_generated": 1,
   "is_virtual": 0,
   "label": "Item Group",
   "length": 0,
   "link_filters": null,
   "mandatory_depends_on": null,
   "modified": "2024-05-27 12:48:08.665875",
   "modified_by": "asaeed@datasofteg.com",
   "module": null,
   "name": "Purchase Order-item_group",
   "no_copy": 0,
   "non_negative": 0,
   "options": "Item Group",
   "owner": "asaeed@datasofteg.com",
   "parent": null,
   "parentfield": null,
   "parenttype": null,
   "permlevel": 0,
   "placeholder": null,
   "precision": "",
   "print_hide": 0,
   "print_hide_if_no_value": 0,
   "print_width": null,
   "read_only": 0,
   "read_only_depends_on": null,
   "report_hide": 0,
   "reqd": 0,
   "search_index": 0,
   "show_dashboard": 0,
   "sort_options": 0,
   "translatable": 1,
   "unique": 0,
   "width": null
  },
  {
   "_assign": null,
   "_comments": null,
   "_liked_by": null,
   "_user_tags": null,
   "allow_in_quick_entry": 0,
   "allow_on_submit": 0,
   "bold": 0,
   "collapsible": 0,
   "collapsible_depends_on": null,
   "columns": 0,
   "creation": "2020-11-05 17:52:28.961998",
   "default": null,
   "depends_on": null,
   "description": null,
   "docstatus": 0,
   "dt": "Purchase Order",
   "fetch_from": null,
   "fetch_if_empty": 0,
   "fieldname": "insert_to_po",
   "fieldtype": "Button",
   "hidden": 0,
   "hide_border": 0,
   "hide_days": 0,
   "hide_seconds": 0,
   "idx": 130,
   "ignore_user_permissions": 0,
   "ignore_xss_filter": 0,
   "in_global_search": 0,
   "in_list_view": 0,
   "in_preview": 0,
   "in_standard_filter": 0,
   "insert_after": "supplier_quotation_item",
   "is_system_generated": 1,
   "is_virtual": 0,
   "label": "Insert to PO",
   "length": 0,
   "link_filters": null,
   "mandatory_depends_on": null,
   "modified": "2020-11-05 17:52:28.961998",
   "modified_by": "Administrator",
   "module": null,
   "name": "Purchase Order-insert_to_po",
   "no_copy": 0,
   "non_negative": 0,
   "options": null,
   "owner": "Administrator",
   "parent": null,
   "parentfield": null,
   "parenttype": null,
   "permlevel": 0,
   "placeholder": null,
   "precision": "",
   "print_hide": 0,
   "print_hide_if_no_value": 0,
   "print_width": null,
   "read_only": 0,
   "read_only_depends_on": null,
   "report_hide": 0,
   "reqd": 0,
   "search_index": 0,
   "show_dashboard": 0,
   "sort_options": 0,
   "translatable": 0,
   "unique": 0,
   "width": null
  },
  {
   "_assign": null,
   "_comments": null,
   "_liked_by": null,
   "_user_tags": null,
   "allow_in_quick_entry": 0,
   "allow_on_submit": 0,
   "bold": 0,
   "collapsible": 0,
   "collapsible_depends_on": null,
   "columns": 0,
   "creation": "2020-11-05 17:52:27.997357",
   "default": null,
   "depends_on": null,
   "description": null,
   "docstatus": 0,
   "dt": "Purchase Order",
   "fetch_from": null,
   "fetch_if_empty": 0,
   "fieldname": "supplier_quotation_item",
   "fieldtype": "Table",
   "hidden": 0,
   "hide_border": 0,
   "hide_days": 0,
   "hide_seconds": 0,
   "idx": 129,
   "ignore_user_permissions": 0,
   "ignore_xss_filter": 0,
   "in_global_search": 0,
   "in_list_view": 0,
   "in_preview": 0,
   "in_standard_filter": 0,
   "insert_after": "search_in_imp",
   "is_system_generated": 1,
   "is_virtual": 0,
   "label": "Supplier Quotation Item",
   "length": 0,
   "link_filters": null,
   "mandatory_depends_on": null,
   "modified": "2020-11-05 17:52:27.997357",
   "modified_by": "Administrator",
   "module": null,
   "name": "Purchase Order-supplier_quotation_item",
   "no_copy": 0,
   "non_negative": 0,
   "options": "Supplier Quotation Item",
   "owner": "Administrator",
   "parent": null,
   "parentfield": null,
   "parenttype": null,
   "permlevel": 0,
   "placeholder": null,
   "precision": "",
   "print_hide": 0,
   "print_hide_if_no_value": 0,
   "print_width": null,
   "read_only": 0,
   "read_only_depends_on": null,
   "report_hide": 0,
   "reqd": 0,
   "search_index": 0,
   "show_dashboard": 0,
   "sort_options": 0,
   "translatable": 0,
   "unique": 0,
   "width": null
  },
  {
   "_assign": null,
   "_comments": null,
   "_liked_by": null,
   "_user_tags": null,
   "allow_in_quick_entry": 0,
   "allow_on_submit": 0,
   "bold": 0,
   "collapsible": 0,
   "collapsible_depends_on": null,
   "columns": 0,
   "creation": "2020-11-05 17:50:37.325054",
   "default": null,
   "depends_on": null,
   "description": null,
   "docstatus": 0,
   "dt": "Purchase Order",
   "fetch_from": null,
   "fetch_if_empty": 0,
   "fieldname": "search_in_imp",
   "fieldtype": "Button",
   "hidden": 0,
   "hide_border": 0,
   "hide_days": 0,
   "hide_seconds": 0,
   "idx": 128,
   "ignore_user_permissions": 0,
   "ignore_xss_filter": 0,
   "in_global_search": 0,
   "in_list_view": 0,
   "in_preview": 0,
   "in_standard_filter": 0,
   "insert_after": "item",
   "is_system_generated": 1,
   "is_virtual": 0,
   "label": "Search in IMP",
   "length": 0,
   "link_filters": null,
   "mandatory_depends_on": null,
   "modified": "2020-11-05 17:50:37.325054",
   "modified_by": "Administrator",
   "module": null,
   "name": "Purchase Order-search_in_imp",
   "no_copy": 0,
   "non_negative": 0,
   "options": null,
   "owner": "Administrator",
   "parent": null,
   "parentfield": null,
   "parenttype": null,
   "permlevel": 0,
   "placeholder": null,
   "precision": "",
   "print_hide": 0,
   "print_hide_if_no_value": 0,
   "print_width": null,
   "read_only": 0,
   "read_only_depends_on": null,
   "report_hide": 0,
   "reqd": 0,
   "search_index": 0,
   "show_dashboard": 0,
   "sort_options": 0,
   "translatable": 0,
   "unique": 0,
   "width": null
  },
  {
   "_assign": null,
   "_comments": null,
   "_liked_by": null,
   "_user_tags": null,
   "allow_in_quick_entry": 0,
   "allow_on_submit": 0,
   "bold": 0,
   "collapsible": 0,
   "collapsible_depends_on": null,
   "columns": 0,
   "creation": "2020-11-05 17:50:36.252321",
   "default": null,
   "depends_on": null,
   "description": null,
   "docstatus": 0,
   "dt": "Purchase Order",
   "fetch_from": null,
   "fetch_if_empty": 0,
   "fieldname": "item",
   "fieldtype": "Link",
   "hidden": 0,
   "hide_border": 0,
   "hide_days": 0,
   "hide_seconds": 0,
   "idx": 127,
   "ignore_user_permissions": 0,
   "ignore_xss_filter": 0,
   "in_global_search": 0,
   "in_list_view": 0,
   "in_preview": 0,
   "in_standard_filter": 0,
   "insert_after": "get_item_from_imp",
   "is_system_generated": 1,
   "is_virtual": 0,
   "label": "Item",
   "length": 0,
   "link_filters": null,
   "mandatory_depends_on": null,
   "modified": "2020-11-05 17:50:36.252321",
   "modified_by": "Administrator",
   "module": null,
   "name": "Purchase Order-item",
   "no_copy": 0,
   "non_negative": 0,
   "options": "Item",
   "owner": "Administrator",
   "parent": null,
   "parentfield": null,
   "parenttype": null,
   "permlevel": 0,
   "placeholder": null,
   "precision": "",
   "print_hide": 0,
   "print_hide_if_no_value": 0,
   "print_width": null,
   "read_only": 0,
   "read_only_depends_on": null,
   "report_hide": 0,
   "reqd": 0,
   "search_index": 0,
   "show_dashboard": 0,
   "sort_options": 0,
   "translatable": 0,
   "unique": 0,
   "width": null
  },
  {
   "_assign": null,
   "_comments": null,
   "_liked_by": null,
   "_user_tags": null,
   "allow_in_quick_entry": 0,
   "allow_on_submit": 0,
   "bold": 0,
   "collapsible": 1,
   "collapsible_depends_on": null,
   "columns": 0,
   "creation": "2020-11-05 17:48:48.518860",
   "default": null,
   "depends_on": null,
   "description": null,
   "docstatus": 0,
   "dt": "Purchase Order",
   "fetch_from": null,
   "fetch_if_empty": 0,
   "fieldname": "get_item_from_imp",
   "fieldtype": "Section Break",
   "hidden": 0,
   "hide_border": 0,
   "hide_days": 0,
   "hide_seconds": 0,
   "idx": 126,
   "ignore_user_permissions": 0,
   "ignore_xss_filter": 0,
   "in_global_search": 0,
   "in_list_view": 0,
   "in_preview": 0,
   "in_standard_filter": 0,
   "insert_after": "customer_contact_email",
   "is_system_generated": 1,
   "is_virtual": 0,
   "label": "Get Item from IMP",
   "length": 0,
   "link_filters": null,
   "mandatory_depends_on": null,
   "modified": "2020-11-05 17:48:48.518860",
   "modified_by": "Administrator",
   "module": null,
   "name": "Purchase Order-get_item_from_imp",
   "no_copy": 0,
   "non_negative": 0,
   "options": null,
   "owner": "Administrator",
   "parent": null,
   "parentfield": null,
   "parenttype": null,
   "permlevel": 0,
   "placeholder": null,
   "precision": "",
   "print_hide": 0,
   "print_hide_if_no_value": 0,
   "print_width": null,
   "read_only": 0,
   "read_only_depends_on": null,
   "report_hide": 0,
   "reqd": 0,
   "search_index": 0,
   "show_dashboard": 0,
   "sort_options": 0,
   "translatable": 0,
   "unique": 0,
   "width": null
  },
  {
   "_assign": null,
   "_comments": null,
   "_liked_by": null,
   "_user_tags": null,
   "allow_in_quick_entry": 0,
   "allow_on_submit": 0,
   "bold": 0,
   "collapsible": 0,
   "collapsible_depends_on": null,
   "columns": 0,
   "creation": "2019-12-24 15:13:12.801551",
   "default": null,
   "depends_on": null,
   "description": null,
   "docstatus": 0,
   "dt": "Purchase Order",
   "fetch_from": null,
   "fetch_if_empty": 0,
   "fieldname": "port_of_destination",
   "fieldtype": "Data",
   "hidden": 1,
   "hide_border": 0,
   "hide_days": 0,
   "hide_seconds": 0,
   "idx": 14,
   "ignore_user_permissions": 0,
   "ignore_xss_filter": 0,
   "in_global_search": 0,
   "in_list_view": 0,
   "in_preview": 0,
   "in_standard_filter": 0,
   "insert_after": "incoterms",
   "is_system_generated": 1,
   "is_virtual": 0,
   "label": "Port of destination",
   "length": 0,
   "link_filters": null,
   "mandatory_depends_on": null,
   "modified": "2019-12-24 15:13:12.801551",
   "modified_by": "Administrator",
   "module": null,
   "name": "Purchase Order-port_of_destination",
   "no_copy": 0,
   "non_negative": 0,
   "options": null,
   "owner": "Administrator",
   "parent": null,
   "parentfield": null,
   "parenttype": null,
   "permlevel": 0,
   "placeholder": null,
   "precision": "",
   "print_hide": 0,
   "print_hide_if_no_value": 0,
   "print_width": null,
   "read_only": 0,
   "read_only_depends_on": null,
   "report_hide": 0,
   "reqd": 0,
   "search_index": 0,
   "show_dashboard": 0,
   "sort_options": 0,
   "translatable": 1,
   "unique": 0,
   "width": null
  },
  {
   "_assign": null,
   "_comments": null,
   "_liked_by": null,
   "_user_tags": null,
   "allow_in_quick_entry": 0,
   "allow_on_submit": 0,
   "bold": 0,
   "collapsible": 0,
   "collapsible_depends_on": null,
   "columns": 0,
   "creation": "2019-12-24 15:13:11.905855",
   "default": null,
   "depends_on": null,
   "description": null,
   "docstatus": 0,
   "dt": "Purchase Order",
   "fetch_from": null,
   "fetch_if_empty": 0,
   "fieldname": "incoterms",
   "fieldtype": "Data",
   "hidden": 1,
   "hide_border": 0,
   "hide_days": 0,
   "hide_seconds": 0,
   "idx": 13,
   "ignore_user_permissions": 0,
   "ignore_xss_filter": 0,
   "in_global_search": 0,
   "in_list_view": 0,
   "in_preview": 0,
   "in_standard_filter": 0,
   "insert_after": "source_of_supply",
   "is_system_generated": 1,
   "is_virtual": 0,
   "label": "INCOTERMS",
   "length": 0,
   "link_filters": null,
   "mandatory_depends_on": null,
   "modified": "2019-12-24 15:13:11.905855",
   "modified_by": "Administrator",
   "module": null,
   "name": "Purchase Order-incoterms",
   "no_copy": 0,
   "non_negative": 0,
   "options": null,
   "owner": "Administrator",
   "parent": null,
   "parentfield": null,
   "parenttype": null,
   "permlevel": 0,
   "placeholder": null,
   "precision": "",
   "print_hide": 0,
   "print_hide_if_no_value": 0,
   "print_width": null,
   "read_only": 0,
   "read_only_depends_on": null,
   "report_hide": 0,
   "reqd": 0,
   "search_index": 0,
   "show_dashboard": 0,
   "sort_options": 0,
   "translatable": 1,
   "unique": 0,
   "width": null
  },
  {
   "_assign": null,
   "_comments": null,
   "_liked_by": null,
   "_user_tags": null,
   "allow_in_quick_entry": 0,
   "allow_on_submit": 0,
   "bold": 0,
   "collapsible": 0,
   "collapsible_depends_on": null,
   "columns": 0,
   "creation": "2019-12-24 15:12:42.802255",
   "default": null,
   "depends_on": null,
   "description": null,
   "docstatus": 0,
   "dt": "Purchase Order",
   "fetch_from": null,
   "fetch_if_empty": 0,
   "fieldname": "source_of_supply",
   "fieldtype": "Data",
   "hidden": 1,
   "hide_border": 0,
   "hide_days": 0,
   "hide_seconds": 0,
   "idx": 12,
   "ignore_user_permissions": 0,
   "ignore_xss_filter": 0,
   "in_global_search": 0,
   "in_list_view": 0,
   "in_preview": 0,
   "in_standard_filter": 0,
   "insert_after": "origin_of_goods",
   "is_system_generated": 1,
   "is_virtual": 0,
   "label": "Source of supply",
   "length": 0,
   "link_filters": null,
   "mandatory_depends_on": null,
   "modified": "2019-12-24 15:12:42.802255",
   "modified_by": "Administrator",
   "module": null,
   "name": "Purchase Order-source_of_supply",
   "no_copy": 0,
   "non_negative": 0,
   "options": null,
   "owner": "Administrator",
   "parent": null,
   "parentfield": null,
   "parenttype": null,
   "permlevel": 0,
   "placeholder": null,
   "precision": "",
   "print_hide": 0,
   "print_hide_if_no_value": 0,
   "print_width": null,
   "read_only": 0,
   "read_only_depends_on": null,
   "report_hide": 0,
   "reqd": 0,
   "search_index": 0,
   "show_dashboard": 0,
   "sort_options": 0,
   "translatable": 1,
   "unique": 0,
   "width": null
  },
  {
   "_assign": null,
   "_comments": null,
   "_liked_by": null,
   "_user_tags": null,
   "allow_in_quick_entry": 0,
   "allow_on_submit": 0,
   "bold": 0,
   "collapsible": 0,
   "collapsible_depends_on": null,
   "columns": 0,
   "creation": "2019-12-24 15:12:41.907279",
   "default": null,
   "depends_on": null,
   "description": null,
   "docstatus": 0,
   "dt": "Purchase Order",
   "fetch_from": null,
   "fetch_if_empty": 0,
   "fieldname": "origin_of_goods",
   "fieldtype": "Data",
   "hidden": 1,
   "hide_border": 0,
   "hide_days": 0,
   "hide_seconds": 0,
   "idx": 11,
   "ignore_user_permissions": 0,
   "ignore_xss_filter": 0,
   "in_global_search": 0,
   "in_list_view": 0,
   "in_preview": 0,
   "in_standard_filter": 0,
   "insert_after": "aian",
   "is_system_generated": 1,
   "is_virtual": 0,
   "label": "Origin of goods",
   "length": 0,
   "link_filters": null,
   "mandatory_depends_on": null,
   "modified": "2019-12-24 15:12:41.907279",
   "modified_by": "Administrator",
   "module": null,
   "name": "Purchase Order-origin_of_goods",
   "no_copy": 0,
   "non_negative": 0,
   "options": null,
   "owner": "Administrator",
   "parent": null,
   "parentfield": null,
   "parenttype": null,
   "permlevel": 0,
   "placeholder": null,
   "precision": "",
   "print_hide": 0,
   "print_hide_if_no_value": 0,
   "print_width": null,
   "read_only": 0,
   "read_only_depends_on": null,
   "report_hide": 0,
   "reqd": 0,
   "search_index": 0,
   "show_dashboard": 0,
   "sort_options": 0,
   "translatable": 1,
   "unique": 0,
   "width": null
  },
  {
   "_assign": null,
   "_comments": null,
   "_liked_by": null,
   "_user_tags": null,
   "allow_in_quick_entry": 0,
   "allow_on_submit": 0,
   "bold": 0,
   "collapsible": 0,
   "collapsible_depends_on": null,
   "columns": 0,
   "creation": "2019-12-24 14:09:05.969949",
   "default": null,
   "depends_on": null,
   "description": null,
   "docstatus": 0,
   "dt": "Purchase Order",
   "fetch_from": null,
   "fetch_if_empty": 0,
   "fieldname": "aian",
   "fieldtype": "Data",
   "hidden": 1,
   "hide_border": 0,
   "hide_days": 0,
   "hide_seconds": 0,
   "idx": 10,
   "ignore_user_permissions": 0,
   "ignore_xss_filter": 0,
   "in_global_search": 0,
   "in_list_view": 0,
   "in_preview": 0,
   "in_standard_filter": 0,
   "insert_after": "order_confirmation_date",
   "is_system_generated": 1,
   "is_virtual": 0,
   "label": "IMP No",
   "length": 0,
   "link_filters": null,
   "mandatory_depends_on": null,
   "modified": "2019-12-24 14:09:05.969949",
   "modified_by": "Administrator",
   "module": null,
   "name": "Purchase Order-aian",
   "no_copy": 0,
   "non_negative": 0,
   "options": null,
   "owner": "Administrator",
   "parent": null,
   "parentfield": null,
   "parenttype": null,
   "permlevel": 0,
   "placeholder": null,
   "precision": "",
   "print_hide": 0,
   "print_hide_if_no_value": 0,
   "print_width": null,
   "read_only": 0,
   "read_only_depends_on": null,
   "report_hide": 0,
   "reqd": 0,
   "search_index": 0,
   "show_dashboard": 0,
   "sort_options": 0,
   "translatable": 1,
   "unique": 0,
   "width": null
  },
  {
   "_assign": null,
   "_comments": null,
   "_liked_by": null,
   "_user_tags": null,
   "allow_in_quick_entry": 0,
   "allow_on_submit": 0,
   "bold": 0,
   "collapsible": 0,
   "collapsible_depends_on": null,
   "columns": 0,
   "creation": "2019-12-07 15:37:18.219277",
   "default": null,
   "depends_on": null,
   "description": null,
   "docstatus": 0,
   "dt": "Purchase Order",
   "fetch_from": null,
   "fetch_if_empty": 0,
   "fieldname": "po_type",
   "fieldtype": "Select",
   "hidden": 0,
   "hide_border": 0,
   "hide_days": 0,
   "hide_seconds": 0,
   "idx": 21,
   "ignore_user_permissions": 0,
   "ignore_xss_filter": 0,
   "in_global_search": 0,
   "in_list_view": 0,
   "in_preview": 0,
   "in_standard_filter": 0,
   "insert_after": "company",
   "is_system_generated": 1,
   "is_virtual": 0,
   "label": "PO type",
   "length": 0,
   "link_filters": null,
   "mandatory_depends_on": null,
   "modified": "2019-12-07 15:37:18.219277",
   "modified_by": "Administrator",
   "module": null,
   "name": "Purchase Order-po_type",
   "no_copy": 0,
   "non_negative": 0,
   "options": "\nCash In Advance\nLC -\nCollection",
   "owner": "Administrator",
   "parent": null,
   "parentfield": null,
   "parenttype": null,
   "permlevel": 0,
   "placeholder": null,
   "precision": "",
   "print_hide": 0,
   "print_hide_if_no_value": 0,
   "print_width": null,
   "read_only": 0,
   "read_only_depends_on": null,
   "report_hide": 0,
   "reqd": 0,
   "search_index": 0,
   "show_dashboard": 0,
   "sort_options": 0,
   "translatable": 1,
   "unique": 0,
   "width": null
  }
 ],
 "custom_perms": [
  {
   "_assign": null,
   "_comments": null,
   "_liked_by": null,
   "_user_tags": null,
   "amend": 1,
   "cancel": 1,
   "create": 1,
   "creation": "2013-05-21 16:16:39",
   "delete": 1,
   "docstatus": 0,
   "email": 1,
   "export": 0,
   "idx": 2,
   "if_owner": 0,
   "import": 0,
   "modified": "2019-04-16 19:36:26.560484",
   "modified_by": "nado_rml@hotmail.com",
   "name": "6e9460b845",
   "owner": "Administrator",
   "parent": "Purchase Order",
   "parentfield": "permissions",
   "parenttype": "DocType",
   "permlevel": 0,
   "print": 1,
   "read": 1,
   "report": 1,
   "role": "Purchase Manager",
   "select": 0,
   "set_user_permissions": 0,
   "share": 1,
   "submit": 1,
   "write": 1
  },
  {
   "_assign": null,
   "_comments": null,
   "_liked_by": null,
   "_user_tags": null,
   "amend": 0,
   "cancel": 0,
   "create": 0,
   "creation": "2013-05-21 16:16:39",
   "delete": 0,
   "docstatus": 0,
   "email": 0,
   "export": 0,
   "idx": 1,
   "if_owner": 0,
   "import": 0,
   "modified": "2019-04-16 19:36:26.592915",
   "modified_by": "nado_rml@hotmail.com",
   "name": "9740adb66d",
   "owner": "Administrator",
   "parent": "Purchase Order",
   "parentfield": "permissions",
   "parenttype": "DocType",
   "permlevel": 0,
   "print": 0,
   "read": 1,
   "report": 1,
   "role": "Stock User",
   "select": 0,
   "set_user_permissions": 0,
   "share": 0,
   "submit": 0,
   "write": 0
  },
  {
   "_assign": null,
   "_comments": null,
   "_liked_by": null,
   "_user_tags": null,
   "amend": 1,
   "cancel": 1,
   "create": 1,
   "creation": "2013-05-21 16:16:39",
   "delete": 1,
   "docstatus": 0,
   "email": 1,
   "export": 0,
   "idx": 3,
   "if_owner": 0,
   "import": 0,
   "modified": "2019-04-16 19:36:26.610372",
   "modified_by": "nado_rml@hotmail.com",
   "name": "061a34b61c",
   "owner": "Administrator",
   "parent": "Purchase Order",
   "parentfield": "permissions",
   "parenttype": "DocType",
   "permlevel": 0,
   "print": 1,
   "read": 1,
   "report": 1,
   "role": "Purchase User",
   "select": 0,
   "set_user_permissions": 0,
   "share": 1,
   "submit": 1,
   "write": 1
  },
  {
   "_assign": null,
   "_comments": null,
   "_liked_by": null,
   "_user_tags": null,
   "amend": 0,
   "cancel": 0,
   "create": 0,
   "creation": "2013-05-21 16:16:39",
   "delete": 0,
   "docstatus": 0,
   "email": 0,
   "export": 0,
   "idx": 4,
   "if_owner": 0,
   "import": 0,
   "modified": "2019-04-16 19:36:26.627462",
   "modified_by": "nado_rml@hotmail.com",
   "name": "ff4a38cb45",
   "owner": "Administrator",
   "parent": "Purchase Order",
   "parentfield": "permissions",
   "parenttype": "DocType",
   "permlevel": 1,
   "print": 0,
   "read": 1,
   "report": 0,
   "role": "Purchase Manager",
   "select": 0,
   "set_user_permissions": 0,
   "share": 0,
   "submit": 0,
   "write": 1
  },
  {
   "_assign": null,
   "_comments": null,
   "_liked_by": null,
   "_user_tags": null,
   "amend": 0,
   "cancel": 0,
   "create": 0,
   "creation": "2019-04-16 19:36:26.658219",
   "delete": 0,
   "docstatus": 0,
   "email": 0,
   "export": 0,
   "idx": 0,
   "if_owner": 0,
   "import": 0,
   "modified": "2019-04-16 19:36:26.658219",
   "modified_by": "nado_rml@hotmail.com",
   "name": "6c29e19a44",
   "owner": "nado_rml@hotmail.com",
   "parent": "Purchase Order",
   "parentfield": "permissions",
   "parenttype": "DocType",
   "permlevel": 0,
   "print": 0,
   "read": 0,
   "report": 0,
   "role": "secretary",
   "select": 0,
   "set_user_permissions": 0,
   "share": 0,
   "submit": 0,
   "write": 0
  }
 ],
 "doctype": "Purchase Order",
 "links": [],
 "property_setters": [
  {
   "_assign": null,
   "_comments": null,
   "_liked_by": null,
   "_user_tags": null,
   "creation": "2025-02-09 11:17:01.537266",
   "default_value": null,
   "doc_type": "Purchase Order",
   "docstatus": 0,
   "doctype_or_field": "DocField",
   "field_name": "schedule_date",
   "idx": 0,
   "is_system_generated": 0,
   "modified": "2025-02-09 11:17:01.537266",
   "modified_by": "Administrator",
   "module": null,
   "name": "Purchase Order-schedule_date-default",
   "owner": "Administrator",
   "parent": null,
   "parentfield": null,
   "parenttype": null,
   "property": "default",
   "property_type": "Text",
   "row_name": null,
   "value": "Today"
  },
  {
   "_assign": null,
   "_comments": null,
   "_liked_by": null,
   "_user_tags": null,
   "creation": "2025-02-03 14:34:30.572879",
   "default_value": null,
   "doc_type": "Purchase Order",
   "docstatus": 0,
   "doctype_or_field": "DocField",
   "field_name": "set_warehouse",
   "idx": 0,
   "is_system_generated": 0,
   "modified": "2025-02-03 14:34:30.572879",
   "modified_by": "Administrator",
   "module": null,
   "name": "Purchase Order-set_warehouse-default",
   "owner": "Administrator",
   "parent": null,
   "parentfield": null,
   "parenttype": null,
   "property": "default",
   "property_type": "Text",
   "row_name": null,
   "value": ""
  },
  {
   "_assign": null,
   "_comments": null,
   "_liked_by": null,
   "_user_tags": null,
   "creation": "2025-02-03 14:34:30.203280",
   "default_value": null,
   "doc_type": "Purchase Order",
   "docstatus": 0,
   "doctype_or_field": "DocType",
   "field_name": null,
   "idx": 0,
   "is_system_generated": 0,
   "modified": "2025-02-03 14:34:30.203280",
   "modified_by": "Administrator",
   "module": null,
   "name": "Purchase Order-main-field_order",
   "owner": "Administrator",
   "parent": null,
   "parentfield": null,
   "parenttype": null,
   "property": "field_order",
   "property_type": "Data",
   "row_name": null,
   "value": "[\"supplier_section\", \"title\", \"naming_series\", \"supplier\", \"supplier_name\", \"order_confirmation_no\", \"order_confirmation_date\", \"aian\", \"origin_of_goods\", \"source_of_supply\", \"incoterms\", \"port_of_destination\", \"get_items_from_open_material_requests\", \"column_break_7\", \"transaction_date\", \"schedule_date\", \"column_break1\", \"company\", \"po_type\", \"apply_tds\", \"tax_withholding_category\", \"is_subcontracted\", \"supplier_warehouse\", \"amended_from\", \"accounting_dimensions_section\", \"item_group\", \"cost_center\", \"dimension_col_break\", \"project\", \"currency_and_price_list\", \"currency\", \"conversion_rate\", \"cb_price_list\", \"buying_price_list\", \"price_list_currency\", \"plc_conversion_rate\", \"ignore_pricing_rule\", \"before_items_section\", \"scan_barcode\", \"set_from_warehouse\", \"items_col_break\", \"set_warehouse\", \"items_section\", \"items\", \"sb_last_purchase\", \"total_qty\", \"total_net_weight\", \"column_break_40\", \"base_total\", \"base_net_total\", \"column_break_26\", \"total\", \"net_total\", \"tax_withholding_net_total\", \"base_tax_withholding_net_total\", \"section_break_48\", \"pricing_rules\", \"raw_material_details\", \"set_reserve_warehouse\", \"supplied_items\", \"taxes_section\", \"tax_category\", \"taxes_and_charges\", \"column_break_53\", \"shipping_rule\", \"column_break_50\", \"incoterm\", \"named_place\", \"section_break_52\", \"taxes\", \"totals\", \"base_taxes_and_charges_added\", \"base_taxes_and_charges_deducted\", \"base_total_taxes_and_charges\", \"column_break_39\", \"taxes_and_charges_added\", \"taxes_and_charges_deducted\", \"total_taxes_and_charges\", \"totals_section\", \"base_grand_total\", \"base_rounding_adjustment\", \"base_in_words\", \"base_rounded_total\", \"column_break4\", \"grand_total\", \"rounding_adjustment\", \"rounded_total\", \"disable_rounded_total\", \"in_words\", \"advance_paid\", \"discount_section\", \"apply_discount_on\", \"base_discount_amount\", \"column_break_45\", \"additional_discount_percentage\", \"discount_amount\", \"sec_tax_breakup\", \"other_charges_calculation\", \"address_and_contact_tab\", \"section_addresses\", \"supplier_address\", \"address_display\", \"col_break_address\", \"contact_person\", \"contact_display\", \"contact_mobile\", \"contact_email\", \"shipping_address_section\", \"shipping_address\", \"column_break_99\", \"shipping_address_display\", \"company_billing_address_section\", \"billing_address\", \"column_break_103\", \"billing_address_display\", \"drop_ship\", \"customer\", \"customer_name\", \"column_break_19\", \"customer_contact_person\", \"customer_contact_display\", \"customer_contact_mobile\", \"customer_contact_email\", \"get_item_from_imp\", \"item\", \"search_in_imp\", \"supplier_quotation_item\", \"insert_to_po\", \"terms_tab\", \"payment_schedule_section\", \"payment_terms_template\", \"payment_schedule\", \"terms_section_break\", \"tc_name\", \"terms\", \"more_info_tab\", \"tracking_section\", \"status\", \"column_break_75\", \"per_billed\", \"per_received\", \"column_break5\", \"letter_head\", \"group_same_items\", \"column_break_86\", \"select_print_heading\", \"language\", \"subscription_section\", \"from_date\", \"to_date\", \"column_break_97\", \"auto_repeat\", \"update_auto_repeat_reference\", \"additional_info_section\", \"is_internal_supplier\", \"represents_company\", \"ref_sq\", \"column_break_74\", \"party_account_currency\", \"inter_company_order_reference\", \"is_old_subcontracting_flow\", \"connections_tab\"]"
  },
  {
   "_assign": null,
   "_comments": null,
   "_liked_by": null,
   "_user_tags": null,
   "creation": "2024-05-06 09:23:27.954202",
   "default_value": null,
   "doc_type": "Purchase Order",
   "docstatus": 0,
   "doctype_or_field": "DocField",
   "field_name": "in_words",
   "idx": 0,
   "is_system_generated": 0,
   "modified": "2024-05-06 09:23:27.954202",
   "modified_by": "sherif@oncopharmegy.com",
   "module": null,
   "name": "Purchase Order-in_words-print_hide",
   "owner": "sherif@oncopharmegy.com",
   "parent": null,
   "parentfield": null,
   "parenttype": null,
   "property": "print_hide",
   "property_type": "Check",
   "row_name": null,
   "value": "0"
  },
  {
   "_assign": null,
   "_comments": null,
   "_liked_by": null,
   "_user_tags": null,
   "creation": "2024-05-06 09:23:27.852293",
   "default_value": null,
   "doc_type": "Purchase Order",
   "docstatus": 0,
   "doctype_or_field": "DocField",
   "field_name": "in_words",
   "idx": 0,
   "is_system_generated": 0,
   "modified": "2024-05-06 09:23:27.852293",
   "modified_by": "sherif@oncopharmegy.com",
   "module": null,
   "name": "Purchase Order-in_words-hidden",
   "owner": "sherif@oncopharmegy.com",
   "parent": null,
   "parentfield": null,
   "parenttype": null,
   "property": "hidden",
   "property_type": "Check",
   "row_name": null,
   "value": "0"
  },
  {
   "_assign": null,
   "_comments": null,
   "_liked_by": null,
   "_user_tags": null,
   "creation": "2024-05-06 09:23:25.685055",
   "default_value": null,
   "doc_type": "Purchase Order",
   "docstatus": 0,
   "doctype_or_field": "DocField",
   "field_name": "disable_rounded_total",
   "idx": 0,
   "is_system_generated": 0,
   "modified": "2024-05-06 09:23:25.685055",
   "modified_by": "sherif@oncopharmegy.com",
   "module": null,
   "name": "Purchase Order-disable_rounded_total-default",
   "owner": "sherif@oncopharmegy.com",
   "parent": null,
   "parentfield": null,
   "parenttype": null,
   "property": "default",
   "property_type": "Text",
   "row_name": null,
   "value": "0"
  },
  {
   "_assign": null,
   "_comments": null,
   "_liked_by": null,
   "_user_tags": null,
   "creation": "2024-05-06 09:23:25.580024",
   "default_value": null,
   "doc_type": "Purchase Order",
   "docstatus": 0,
   "doctype_or_field": "DocField",
   "field_name": "rounded_total",
   "idx": 0,
   "is_system_generated": 0,
   "modified": "2024-05-06 09:23:25.580024",
   "modified_by": "sherif@oncopharmegy.com",
   "module": null,
   "name": "Purchase Order-rounded_total-print_hide",
   "owner": "sherif@oncopharmegy.com",
   "parent": null,
   "parentfield": null,
   "parenttype": null,
   "property": "print_hide",
   "property_type": "Check",
   "row_name": null,
   "value": "0"
  },
  {
   "_assign": null,
   "_comments": null,
   "_liked_by": null,
   "_user_tags": null,
   "creation": "2024-05-06 09:23:25.474484",
   "default_value": null,
   "doc_type": "Purchase Order",
   "docstatus": 0,
   "doctype_or_field": "DocField",
   "field_name": "rounded_total",
   "idx": 0,
   "is_system_generated": 0,
   "modified": "2024-05-06 09:23:25.474484",
   "modified_by": "sherif@oncopharmegy.com",
   "module": null,
   "name": "Purchase Order-rounded_total-hidden",
   "owner": "sherif@oncopharmegy.com",
   "parent": null,
   "parentfield": null,
   "parenttype": null,
   "property": "hidden",
   "property_type": "Check",
   "row_name": null,
   "value": "0"
  },
  {
   "_assign": null,
   "_comments": null,
   "_liked_by": null,
   "_user_tags": null,
   "creation": "2024-05-06 09:23:25.369586",
   "default_value": null,
   "doc_type": "Purchase Order",
   "docstatus": 0,
   "doctype_or_field": "DocField",
   "field_name": "base_rounded_total",
   "idx": 0,
   "is_system_generated": 0,
   "modified": "2024-05-06 09:23:25.369586",
   "modified_by": "sherif@oncopharmegy.com",
   "module": null,
   "name": "Purchase Order-base_rounded_total-print_hide",
   "owner": "sherif@oncopharmegy.com",
   "parent": null,
   "parentfield": null,
   "parenttype": null,
   "property": "print_hide",
   "property_type": "Check",
   "row_name": null,
   "value": "1"
  },
  {
   "_assign": null,
   "_comments": null,
   "_liked_by": null,
   "_user_tags": null,
   "creation": "2024-05-06 09:23:25.264063",
   "default_value": null,
   "doc_type": "Purchase Order",
   "docstatus": 0,
   "doctype_or_field": "DocField",
   "field_name": "base_rounded_total",
   "idx": 0,
   "is_system_generated": 0,
   "modified": "2024-05-06 09:23:25.264063",
   "modified_by": "sherif@oncopharmegy.com",
   "module": null,
   "name": "Purchase Order-base_rounded_total-hidden",
   "owner": "sherif@oncopharmegy.com",
   "parent": null,
   "parentfield": null,
   "parenttype": null,
   "property": "hidden",
   "property_type": "Check",
   "row_name": null,
   "value": "0"
  },
  {
   "_assign": null,
   "_comments": null,
   "_liked_by": null,
   "_user_tags": null,
   "creation": "2023-12-05 13:42:04.295451",
   "default_value": null,
   "doc_type": "Purchase Order",
   "docstatus": 0,
   "doctype_or_field": "DocField",
   "field_name": "payment_schedule",
   "idx": 0,
   "is_system_generated": 0,
   "modified": "2023-12-05 13:42:04.295451",
   "modified_by": "sherif@oncopharmegy.com",
   "module": null,
   "name": "Purchase Order-payment_schedule-print_hide",
   "owner": "sherif@oncopharmegy.com",
   "parent": null,
   "parentfield": null,
   "parenttype": null,
   "property": "print_hide",
   "property_type": "Check",
   "row_name": null,
   "value": "1"
  },
  {
   "_assign": null,
   "_comments": null,
   "_liked_by": null,
   "_user_tags": null,
   "creation": "2023-12-05 13:42:04.236207",
   "default_value": null,
   "doc_type": "Purchase Order",
   "docstatus": 0,
   "doctype_or_field": "DocField",
   "field_name": "due_date",
   "idx": 0,
   "is_system_generated": 0,
   "modified": "2023-12-05 13:42:04.236207",
   "modified_by": "sherif@oncopharmegy.com",
   "module": null,
   "name": "Purchase Order-due_date-print_hide",
   "owner": "sherif@oncopharmegy.com",
   "parent": null,
   "parentfield": null,
   "parenttype": null,
   "property": "print_hide",
   "property_type": "Check",
   "row_name": null,
   "value": "0"
  },
  {
   "_assign": null,
   "_comments": null,
   "_liked_by": null,
   "_user_tags": null,
   "creation": "2023-07-24 11:16:10.189642",
   "default_value": null,
   "doc_type": "Purchase Order",
   "docstatus": 0,
   "doctype_or_field": "DocField",
   "field_name": "scan_barcode",
   "idx": 0,
   "is_system_generated": 1,
   "modified": "2023-07-24 11:16:10.189642",
   "modified_by": "asaeed@datasofteg.com",
   "module": null,
   "name": "Purchase Order-scan_barcode-hidden",
   "owner": "asaeed@datasofteg.com",
   "parent": null,
   "parentfield": null,
   "parenttype": null,
   "property": "hidden",
   "property_type": "Check",
   "row_name": null,
   "value": "0"
  },
  {
   "_assign": null,
   "_comments": null,
   "_liked_by": null,
   "_user_tags": null,
   "creation": "2020-11-05 16:55:00.502795",
   "default_value": null,
   "doc_type": "Purchase Order",
   "docstatus": 0,
   "doctype_or_field": "DocField",
   "field_name": "title",
   "idx": 0,
   "is_system_generated": 0,
   "modified": "2020-11-05 16:55:00.502795",
   "modified_by": "asaeed@datasofteg.com",
   "module": null,
   "name": "Purchase Order-title-in_global_search",
   "owner": "asaeed@datasofteg.com",
   "parent": null,
   "parentfield": null,
   "parenttype": null,
   "property": "in_global_search",
   "property_type": "Check",
   "row_name": null,
   "value": "1"
  },
  {
   "_assign": null,
   "_comments": null,
   "_liked_by": null,
   "_user_tags": null,
   "creation": "2020-11-05 16:55:00.480923",
   "default_value": null,
   "doc_type": "Purchase Order",
   "docstatus": 0,
   "doctype_or_field": "DocField",
   "field_name": "title",
   "idx": 0,
   "is_system_generated": 0,
   "modified": "2020-11-05 16:55:00.480923",
   "modified_by": "asaeed@datasofteg.com",
   "module": null,
   "name": "Purchase Order-title-in_list_view",
   "owner": "asaeed@datasofteg.com",
   "parent": null,
   "parentfield": null,
   "parenttype": null,
   "property": "in_list_view",
   "property_type": "Check",
   "row_name": null,
   "value": "1"
  },
  {
   "_assign": null,
   "_comments": null,
   "_liked_by": null,
   "_user_tags": null,
   "creation": "2020-11-05 16:54:59.970185",
   "default_value": null,
   "doc_type": "Purchase Order",
   "docstatus": 0,
   "doctype_or_field": "DocField",
   "field_name": "title",
   "idx": 0,
   "is_system_generated": 0,
   "modified": "2020-11-05 16:54:59.970185",
   "modified_by": "asaeed@datasofteg.com",
   "module": null,
   "name": "Purchase Order-title-in_standard_filter",
   "owner": "asaeed@datasofteg.com",
   "parent": null,
   "parentfield": null,
   "parenttype": null,
   "property": "in_standard_filter",
   "property_type": "Check",
   "row_name": null,
   "value": "1"
  },
  {
   "_assign": null,
   "_comments": null,
   "_liked_by": null,
   "_user_tags": null,
   "creation": "2019-11-30 09:36:09.650188",
   "default_value": null,
   "doc_type": "Purchase Order",
   "docstatus": 0,
   "doctype_or_field": "DocField",
   "field_name": "naming_series",
   "idx": 0,
   "is_system_generated": 1,
   "modified": "2020-11-05 16:41:28.741365",
   "modified_by": "Administrator",
   "module": null,
   "name": "Purchase Order-naming_series-options",
   "owner": "Administrator",
   "parent": null,
   "parentfield": null,
   "parenttype": null,
   "property": "options",
   "property_type": "Text",
   "row_name": null,
   "value": "PO-.YYYY.-"
  },
  {
   "_assign": null,
   "_comments": null,
   "_liked_by": null,
   "_user_tags": null,
   "creation": "2020-11-04 15:19:35.148697",
   "default_value": null,
   "doc_type": "Purchase Order",
   "docstatus": 0,
   "doctype_or_field": "DocField",
   "field_name": "naming_series",
   "idx": 0,
   "is_system_generated": 0,
   "modified": "2020-11-05 16:41:28.689325",
   "modified_by": "Administrator",
   "module": null,
   "name": "Purchase Order-naming_series-default",
   "owner": "sherif@oncopharmegy.com",
   "parent": null,
   "parentfield": null,
   "parenttype": null,
   "property": "default",
   "property_type": "Text",
   "row_name": null,
   "value": "PO-.YYYY.-"
  },
  {
   "_assign": null,
   "_comments": null,
   "_liked_by": null,
   "_user_tags": null,
   "creation": "2019-12-24 14:14:28.219653",
   "default_value": null,
   "doc_type": "Purchase Order",
   "docstatus": 0,
   "doctype_or_field": "DocType",
   "field_name": null,
   "idx": 0,
   "is_system_generated": 1,
   "modified": "2019-12-24 14:14:28.219653",
   "modified_by": "Administrator",
   "module": null,
   "name": "Purchase Order-default_print_format",
   "owner": "Administrator",
   "parent": null,
   "parentfield": null,
   "parenttype": null,
   "property": "default_print_format",
   "property_type": "Data",
   "row_name": null,
   "value": "ONCO PO  FORMAT"
  }
 ],
 "sync_on_migrate": 1
}